pypix/__init__.py
pypix/pix.py
pypix-0.2.0.dist-info/LICENSE
pypix-0.2.0.dist-info/METADATA
pypix-0.2.0.dist-info/WHEEL
pypix-0.2.0.dist-info/RECORD
