Metadata-Version: 2.3
Name: pypix
Version: 0.2.0
Summary: Python library for generating pix codes with CRC16 validation
License: GPL-3.0 License
Keywords: pix,banco-central,pagamento,payment
Author: Daniel Yohan
Author-email: dyohan9@gmail.com
Requires-Python: >=3.9,<3.13
Classifier: Development Status :: 4 - Beta
Classifier: Intended Audience :: Developers
Classifier: License :: OSI Approved :: GNU General Public License v3 (GPLv3)
Classifier: License :: Other/Proprietary License
Classifier: Programming Language :: Python
Classifier: Programming Language :: Python :: 3
Classifier: Programming Language :: Python :: 3.9
Classifier: Programming Language :: Python :: 3.10
Classifier: Programming Language :: Python :: 3.11
Classifier: Programming Language :: Python :: 3.12
Classifier: Topic :: Software Development :: Libraries
Project-URL: Repository, https://github.com/dyohan9/python-pix
